pca_b_stream/__init__.py
pca_b_stream/cli.py
pca_b_stream/main.py
pca_b_stream/version.py
pca_b_stream/config/nicegui.py
pca_b_stream/constant/nicegui.py
pca_b_stream/constant/numpy_.py
pca_b_stream/constant/project.py
pca_b_stream/nicegui/main.py
pca_b_stream-2025.6.dist-info/METADATA
pca_b_stream-2025.6.dist-info/WHEEL
pca_b_stream-2025.6.dist-info/entry_points.txt
pca_b_stream-2025.6.dist-info/top_level.txt
pca_b_stream-2025.6.dist-info/RECORD
