Metadata-Version: 2.4
Name: pca-b-stream
Version: 2025.6
Summary: Byte Stream Representation of Piecewise-constant Array
Home-page: https://src.koda.cnrs.fr/eric.debreuve/pca-b-stream/
Author: Eric Debreuve
Author-email: eric.debreuve@cnrs.fr
License: CeCILL-2.1
Project-URL: Documentation, https://src.koda.cnrs.fr/eric.debreuve/pca-b-stream/
Project-URL: Source, https://src.koda.cnrs.fr/eric.debreuve/pca-b-stream/
Keywords: array,image,piecewise constant,byte stream
Classifier: Topic :: Scientific/Engineering :: Image Recognition
Classifier: Intended Audience :: Science/Research
Classifier: License :: OSI Approved :: CEA CNRS Inria Logiciel Libre License, version 2.1 (CeCILL-2.1)
Classifier: Programming Language :: Python :: 3
Classifier: Development Status :: 4 - Beta
Requires-Python: >=3.8
Requires-Dist: leb128
Requires-Dist: nicegui
Requires-Dist: numpy
Requires-Dist: pillow
Requires-Dist: scikit-image
Dynamic: author
Dynamic: author-email
Dynamic: classifier
Dynamic: description
Dynamic: description-content-type
Dynamic: home-page
Dynamic: keywords
Dynamic: license
Dynamic: project-url
Dynamic: requires-dist
Dynamic: requires-python
Dynamic: summary
